LICENSE
MANIFEST.in
README.md
requirements.txt
setup.py
nonebot_plugin_covid19_news/__init__.py
nonebot_plugin_covid19_news/data.py
nonebot_plugin_covid19_news/data_load.py
nonebot_plugin_covid19_news/policy.py
nonebot_plugin_covid19_news/tools.py
nonebot_plugin_covid19_news/uilts.py
nonebot_plugin_covid19_news.egg-info/PKG-INFO
nonebot_plugin_covid19_news.egg-info/SOURCES.txt
nonebot_plugin_covid19_news.egg-info/dependency_links.txt
nonebot_plugin_covid19_news.egg-info/requires.txt
nonebot_plugin_covid19_news.egg-info/top_level.txt