Metadata-Version: 2.1
Name: nonebot-plugin-covid19-news
Version: 0.5.4
Summary: nonebot_plugin about covid-19 news
Home-page: https://github.com/Zeta-qixi/nonebot-plugin-covid19-news/
Author: Zeta
Author-email: 
License: MIT Licence
Platform: UNKNOWN
License-File: LICENSE
